dudraw/__init__.py
dudraw/color.py
dudraw/dudraw.py
dudraw-1.10.1.dist-info/METADATA
dudraw-1.10.1.dist-info/WHEEL
dudraw-1.10.1.dist-info/licenses/LICENSE
dudraw-1.10.1.dist-info/RECORD
