Metadata-Version: 2.4
Name: dudraw
Version: 1.10.1
Summary: A fork of Princeton's stddraw for use in classes at the University of Denver
Project-URL: Homepage, https://git.cs.du.edu/dudraw/dudraw
Author-email: Andrew Hannum <andrew.hannum@du.edu>
License-File: LICENSE
Classifier: License :: OSI Approved :: GNU General Public License v3 (GPLv3)
Classifier: Operating System :: OS Independent
Classifier: Programming Language :: Python :: 3
Requires-Python: >=3.8
Requires-Dist: pygame>=2.0.0
